modconfig/__init__.py
modconfig/py.typed
modconfig-1.2.1.dist-info/LICENSE
modconfig-1.2.1.dist-info/METADATA
modconfig-1.2.1.dist-info/WHEEL
modconfig-1.2.1.dist-info/top_level.txt
modconfig-1.2.1.dist-info/RECORD
