Metadata-Version: 2.1
Name: modconfig
Version: 1.2.1
Summary: Simple hierarchic configuration manager for apps
Home-page: https://github.com/klen/modconfig
Author: Kirill Klenov
Author-email: horneds@gmail.com
License: MIT
Project-URL: Documentation, https://github.com/klen/modconfig
Project-URL: Source code, https://github.com/klen/modconfig
Project-URL: Issue tracker, https://github.com/klen/modconfig/issues
Keywords: settings,configuration
Platform: UNKNOWN
Classifier: Development Status :: 5 - Production/Stable
Classifier: Intended Audience :: Developers
Classifier: License :: OSI Approved :: MIT License
Classifier: Programming Language :: Python
Classifier: Programming Language :: Python :: 3
Classifier: Programming Language :: Python :: 3.7
Classifier: Programming Language :: Python :: 3.8
Classifier: Programming Language :: Python :: 3.9
Classifier: Programming Language :: Python :: 3.10
Requires-Python: >=3.7
License-File: LICENSE
Provides-Extra: tests
Requires-Dist: pytest ; extra == 'tests'
Requires-Dist: pytest-mypy ; extra == 'tests'
